{
	"name": "onpremisesqlserver",
	"properties": {
		"annotations": [],
		"type": "SqlServer",
		"typeProperties": {
			"server": "XD\\MSSQLSERVER2024",
			"database": "BikeStores",
			"encrypt": "mandatory",
			"trustServerCertificate": true,
			"authenticationType": "SQL",
			"userName": "seifo",
			"password": {
				"type": "AzureKeyVaultSecret",
				"store": {
					"referenceName": "AzureKeyVault1",
					"type": "LinkedServiceReference"
				},
				"secretName": "password"
			}
		},
		"connectVia": {
			"referenceName": "SHIR",
			"type": "IntegrationRuntimeReference"
		}
	}
}